swarmauri_evaluator_constanttime/ConstantTimeEvaluator.py
swarmauri_evaluator_constanttime/__init__.py
swarmauri_evaluator_constanttime-0.3.0.dev5.dist-info/LICENSE
swarmauri_evaluator_constanttime-0.3.0.dev5.dist-info/METADATA
swarmauri_evaluator_constanttime-0.3.0.dev5.dist-info/WHEEL
swarmauri_evaluator_constanttime-0.3.0.dev5.dist-info/entry_points.txt
swarmauri_evaluator_constanttime-0.3.0.dev5.dist-info/RECORD
